Metadata-Version: 1.1
Name: nx-graph
Version: 0.0.1
Summary: Project Description
Home-page: UNKNOWN
Author: Tiago da Silva <tdsh97@gmail.com>
Author-email: UNKNOWN
License: MIT
Platform: UNKNOWN
Classifier: Framework :: Dash
